README.md
sage/__init__.py
sage/cli/__init__.py
sage/cli/commons.py
sage/cli/debug.py
sage/cli/grpc_server.py
sage/cli/hbase.py
sage/cli/http_server.py
sage/cli/parsers.py
sage/cli/postgres.py
sage/cli/postgres_utils.py
sage/cli/sqlite.py
sage/cli/sqlite_utils.py
sage/cli/utils.py
sage/database/__init__.py
sage/database/core/__init__.py
sage/database/core/dataset.py
sage/database/core/graph.py
sage/database/core/rdf_config.py
sage/database/core/yaml_config.py
sage/database/db_connector.py
sage/database/db_iterator.py
sage/database/descriptors.py
sage/database/estimators.py
sage/database/hbase/__init__.py
sage/database/hbase/connector.py
sage/database/hbase/iterator.py
sage/database/hbase/utils.py
sage/database/hdt/__init__.py
sage/database/hdt/connector.py
sage/database/hdt/iterator.py
sage/database/import_manager.py
sage/database/postgres_backends/__init__.py
sage/database/postgres_backends/connector.py
sage/database/postgres_backends/postgres/__init__.py
sage/database/postgres_backends/postgres/connector.py
sage/database/postgres_backends/postgres/iterator.py
sage/database/postgres_backends/postgres/queries.py
sage/database/postgres_backends/postgres_catalog/__init__.py
sage/database/postgres_backends/postgres_catalog/connector.py
sage/database/postgres_backends/postgres_catalog/iterator.py
sage/database/postgres_backends/postgres_catalog/queries.py
sage/database/postgres_backends/postgres_mvcc/__init__.py
sage/database/postgres_backends/postgres_mvcc/connector.py
sage/database/postgres_backends/postgres_mvcc/iterator.py
sage/database/postgres_backends/postgres_mvcc/queries.py
sage/database/postgres_backends/transaction_manager.py
sage/database/sqlite_backends/__init__.py
sage/database/sqlite_backends/connector.py
sage/database/sqlite_backends/sqlite/__init__.py
sage/database/sqlite_backends/sqlite/connector.py
sage/database/sqlite_backends/sqlite/iterator.py
sage/database/sqlite_backends/sqlite/queries.py
sage/database/sqlite_backends/sqlite_catalog/__init__.py
sage_engine-2.3.0.dist-info/entry_points.txt
sage_engine-2.3.0.dist-info/LICENSE
sage_engine-2.3.0.dist-info/WHEEL
sage_engine-2.3.0.dist-info/METADATA
sage_engine-2.3.0.dist-info/RECORD
