Metadata-Version: 2.1
Name: sage-engine
Version: 2.3.0
Summary: Sage: a preemptive SPARQL query engine for online Knowledge Graphs
Home-page: https://github.com/sage-org/sage-engine
License: MIT
Keywords: rdf,sparql,query engine
Author: Thomas Minier
Author-email: tminier01@gmail.com
Requires-Python: >=3.7,<4.0
Classifier: License :: OSI Approved :: MIT License
Classifier: Programming Language :: Python :: 3
Classifier: Programming Language :: Python :: 3.7
Classifier: Programming Language :: Python :: 3.8
Classifier: Programming Language :: Python :: 3.9
Classifier: Topic :: Database :: Database Engines/Servers
Classifier: Topic :: Internet :: WWW/HTTP :: HTTP Servers
Classifier: Topic :: Scientific/Engineering
Provides-Extra: hbase
Provides-Extra: hdt
Provides-Extra: postgres
Requires-Dist: PyYAML (==5.4.1)
Requires-Dist: click (==7.1.2)
Requires-Dist: coloredlogs (==15.0)
Requires-Dist: fastapi (==0.63.0)
Requires-Dist: grpcio (>=1.36,<2.0)
Requires-Dist: happybase (==1.2.0); extra == "hbase"
Requires-Dist: hdt (==2.3); extra == "hdt"
Requires-Dist: protobuf (==3.15.7)
Requires-Dist: psycopg2-binary (==2.8.6); extra == "postgres"
Requires-Dist: pybind11 (==2.2.4); extra == "hdt"
Requires-Dist: pylru (>=1.0,<2.0)
Requires-Dist: rdflib (==5.0.0)
Requires-Dist: rdflib-jsonld (==0.5.0)
Requires-Dist: uvicorn (==0.13.4)
Requires-Dist: uvloop (==0.15.2)
Project-URL: Repository, https://github.com/sage-org/sage-engine
